wei_print_lol/__init__.py
wei_print_lol/print_lol.py
wei_print_lol-0.0.2.dist-info/METADATA
wei_print_lol-0.0.2.dist-info/WHEEL
wei_print_lol-0.0.2.dist-info/RECORD
