Metadata-Version: 2.1
Name: wei_print_lol
Version: 0.0.2
Summary: Print List
Author-email: Wei <331855608@qq.com>
Classifier: License :: OSI Approved :: MIT License
Classifier: Operating System :: OS Independent
Classifier: Programming Language :: Python :: 3
Requires-Python: >=3.7
